{
  "project_info": {
    "project_number": "806890918157",
    "project_id": "locshare-93a7b",
    "storage_bucket": "locshare-93a7b.firebasestorage.app"
  },
  "client": [
    {
      "client_info": {
        "mobilesdk_app_id": "1:806890918157:android:0c905c57d0f785ab3d6044",
        "android_client_info": {
          "package_name": "com.test.testing"
        }
      },
      "oauth_client": [],
      "api_key": [
        {
          "current_key": "AIzaSyAKhkD6BC6fQ7UoLRz8vnOfqvrd_pdnuig"
        }
      ],
      "services": {
        "appinvite_service": {
          "other_platform_oauth_client": []
        }
      }
    }
  ],
  "configuration_version": "1"
}